schemathesis/__init__.py
schemathesis/auths.py
schemathesis/checks.py
schemathesis/errors.py
schemathesis/filters.py
schemathesis/hooks.py
schemathesis/py.typed
schemathesis/schemas.py
schemathesis/cli/__init__.py
schemathesis/cli/__main__.py
schemathesis/cli/constants.py
schemathesis/cli/core.py
schemathesis/cli/commands/__init__.py
schemathesis/cli/commands/data.py
schemathesis/cli/commands/run/__init__.py
schemathesis/cli/commands/run/context.py
schemathesis/cli/commands/run/events.py
schemathesis/cli/commands/run/executor.py
schemathesis/cli/commands/run/filters.py
schemathesis/cli/commands/run/loaders.py
schemathesis/cli/commands/run/validation.py
schemathesis/cli/commands/run/handlers/__init__.py
schemathesis/cli/commands/run/handlers/base.py
schemathesis/cli/commands/run/handlers/cassettes.py
schemathesis/cli/commands/run/handlers/junitxml.py
schemathesis/cli/commands/run/handlers/ndjson.py
schemathesis/cli/commands/run/handlers/output.py
schemathesis/cli/ext/__init__.py
schemathesis/cli/ext/fs.py
schemathesis/cli/ext/groups.py
schemathesis/cli/ext/options.py
schemathesis/config/__init__.py
schemathesis/config/_auth.py
schemathesis/config/_checks.py
schemathesis/config/_diff_base.py
schemathesis/config/_env.py
schemathesis/config/_error.py
schemathesis/config/_generation.py
schemathesis/config/_health_check.py
schemathesis/config/_operations.py
schemathesis/config/_output.py
schemathesis/config/_parameters.py
schemathesis/config/_phases.py
schemathesis/config/_projects.py
schemathesis/config/_rate_limit.py
schemathesis/config/_report.py
schemathesis/config/_validator.py
schemathesis/config/_warnings.py
schemathesis/config/schema.json
schemathesis/core/__init__.py
schemathesis/core/adapter.py
schemathesis/core/compat.py
schemathesis/core/control.py
schemathesis/core/curl.py
schemathesis/core/deserialization.py
schemathesis/core/errors.py
schemathesis/core/failures.py
schemathesis/core/fs.py
schemathesis/core/hooks.py
schemathesis/core/lazy_import.py
schemathesis-4.9.4.dist-info/METADATA
schemathesis-4.9.4.dist-info/WHEEL
schemathesis-4.9.4.dist-info/entry_points.txt
schemathesis-4.9.4.dist-info/licenses/LICENSE
schemathesis-4.9.4.dist-info/RECORD
