Metadata-Version: 2.4
Name: schemathesis
Version: 4.9.4
Summary: Property-based testing framework for Open API and GraphQL based apps
Project-URL: Documentation, https://schemathesis.readthedocs.io/en/stable/
Project-URL: Changelog, https://github.com/schemathesis/schemathesis/blob/master/CHANGELOG.md
Project-URL: Bug Tracker, https://github.com/schemathesis/schemathesis
Project-URL: Funding, https://github.com/sponsors/Stranger6667
Project-URL: Source Code, https://github.com/schemathesis/schemathesis
Author-email: Dmitry Dygalo <dmitry@dygalo.dev>
Maintainer-email: Dmitry Dygalo <dmitry@dygalo.dev>
License-Expression: MIT
License-File: LICENSE
Keywords: graphql,hypothesis,openapi,pytest,testing
Classifier: Development Status :: 5 - Production/Stable
Classifier: Environment :: Console
Classifier: Framework :: Hypothesis
Classifier: Framework :: Pytest
Classifier: Intended Audience :: Developers
Classifier: License :: OSI Approved :: MIT License
Classifier: Operating System :: OS Independent
Classifier: Programming Language :: Python :: 3 :: Only
Classifier: Programming Language :: Python :: 3.10
Classifier: Programming Language :: Python :: 3.11
Classifier: Programming Language :: Python :: 3.12
Classifier: Programming Language :: Python :: 3.13
Classifier: Programming Language :: Python :: 3.14
Classifier: Programming Language :: Python :: Implementation :: CPython
Classifier: Programming Language :: Python :: Implementation :: PyPy
Classifier: Topic :: Software Development :: Testing
Requires-Python: >=3.10
Requires-Dist: click<9,>=8.0
Requires-Dist: colorama<1.0,>=0.4
Requires-Dist: harfile<1.0,>=0.4.0
Requires-Dist: httpx<1.0,>=0.22.0
Requires-Dist: hypothesis-graphql<1,>=0.11.1
Requires-Dist: hypothesis-jsonschema<0.24,>=0.23.1
Requires-Dist: hypothesis<7,>=6.108.0
Requires-Dist: jsonschema[format]<5.0,>=4.18.0
Requires-Dist: junit-xml<2.0,>=1.9
Requires-Dist: pyrate-limiter<4.0,>=3.0
Requires-Dist: pytest-subtests<0.16.0,>=0.11
Requires-Dist: pytest<10,>=8
Requires-Dist: pyyaml<7.0,>=5.1
Requires-Dist: requests<3,>=2.22
Requires-Dist: rich>=13.9.4
Requires-Dist: starlette-testclient<1,>=0.4.1
Requires-Dist: tenacity<10.0,>=9.1.2
Requires-Dist: tomli>=2.2.1; python_version < '3.11'
Requires-Dist: typing-extensions>=4.12.2
Requires-Dist: werkzeug<4,>=0.16.0
Provides-Extra: bench
Requires-Dist: pytest-codspeed==4.2.0; extra == 'bench'
Provides-Extra: cov
Requires-Dist: coverage-enable-subprocess; extra == 'cov'
Requires-Dist: coverage[toml]>=5.3; extra == 'cov'
Provides-Extra: dev
Requires-Dist: aiohttp<4.0,>=3.9.1; extra == 'dev'
Requires-Dist: coverage-enable-subprocess; extra == 'dev'
Requires-Dist: coverage>=6; extra == 'dev'
Requires-Dist: coverage[toml]>=5.3; extra == 'dev'
Requires-Dist: fastapi>=0.86.0; extra == 'dev'
Requires-Dist: flask<3.0,>=2.1.1; extra == 'dev'
Requires-Dist: hypothesis-openapi<1,>=0.2; (python_version >= '3.10') and extra == 'dev'
Requires-Dist: mkdocs-material; extra == 'dev'
Requires-Dist: mkdocstrings[python]; extra == 'dev'
Requires-Dist: pydantic>=1.10.2; extra == 'dev'
Requires-Dist: pytest-asyncio<2.0,>=1.0; extra == 'dev'
Requires-Dist: pytest-codspeed==4.2.0; extra == 'dev'
Requires-Dist: pytest-httpserver<2.0,>=1.0; extra == 'dev'
Requires-Dist: pytest-mock<4.0,>=3.7.0; extra == 'dev'
Requires-Dist: pytest-trio<1.0,>=0.8; extra == 'dev'
Requires-Dist: pytest-xdist<4.0,>=3; extra == 'dev'
Requires-Dist: strawberry-graphql[fastapi]>=0.109.0; extra == 'dev'
Requires-Dist: syrupy<6.0,>=4; extra == 'dev'
Requires-Dist: tomli-w>=1.2.0; extra == 'dev'
Requires-Dist: trustme<1.0,>=0.9.0; extra == 'dev'
Provides-Extra: docs
Requires-Dist: mkdocs-material; extra == 'docs'
Requires-Dist: mkdocstrings[python]; extra == 'docs'
Provides-Extra: tests
Requires-Dist: aiohttp<4.0,>=3.9.1; extra == 'tests'
Requires-Dist: coverage>=6; extra == 'tests'
Requires-Dist: fastapi>=0.86.0; extra == 'tests'
Requires-Dist: flask<3.0,>=2.1.1; extra == 'tests'
Requires-Dist: hypothesis-openapi<1,>=0.2; (python_version >= '3.10') and extra == 'tests'
Requires-Dist: pydantic>=1.10.2; extra == 'tests'
Requires-Dist: pytest-asyncio<2.0,>=1.0; extra == 'tests'
Requires-Dist: pytest-httpserver<2.0,>=1.0; extra == 'tests'
Requires-Dist: pytest-mock<4.0,>=3.7.0; extra == 'tests'
Requires-Dist: pytest-trio<1.0,>=0.8; extra == 'tests'
Requires-Dist: pytest-xdist<4.0,>=3; extra == 'tests'
Requires-Dist: strawberry-graphql[fastapi]>=0.109.0; extra == 'tests'
Requires-Dist: syrupy<6.0,>=4; extra == 'tests'
Requires-Dist: tomli-w>=1.2.0; extra == 'tests'
Requires-Dist: trustme<1.0,>=0.9.0; extra == 'tests'
